nonebot_plugin_price_checker/__init__.py
nonebot_plugin_price_checker/config.py
nonebot_plugin_price_checker/crawler.py
nonebot_plugin_price_checker/renderer.py
nonebot_plugin_price_checker-0.1.2.dist-info/METADATA
nonebot_plugin_price_checker-0.1.2.dist-info/WHEEL
nonebot_plugin_price_checker-0.1.2.dist-info/entry_points.txt
nonebot_plugin_price_checker-0.1.2.dist-info/top_level.txt
nonebot_plugin_price_checker-0.1.2.dist-info/RECORD
